setup.py
arpita_indian_states_25/__init__.py
arpita_indian_states_25/asgi.py
arpita_indian_states_25/settings.py
arpita_indian_states_25/urls.py
arpita_indian_states_25/wsgi.py
arpita_indian_states_25.egg-info/PKG-INFO
arpita_indian_states_25.egg-info/SOURCES.txt
arpita_indian_states_25.egg-info/dependency_links.txt
arpita_indian_states_25.egg-info/requires.txt
arpita_indian_states_25.egg-info/top_level.txt
ast1/__init__.py
ast1/admin.py
ast1/apps.py
ast1/fields.py
ast1/forms.py
ast1/models.py
ast1/states.py
ast1/tests.py
ast1/views.py
ast1/migrations/__init__.py