Metadata-Version: 2.1
Name: arpita_indian_states_25
Version: 0.1
Summary: A Django app that provides Indian state choices as a model and form field.
Author: Arpita Hatkar
Author-email: arpitahatkar1415@gmail.com
License: MT
Classifier: Framework :: Django
Classifier: Programming Language :: Python :: 3
Requires-Dist: django
